papagei/__init__.py
papagei/papagei.py
papagei_niederha-0.0.2.dist-info/LICENSE
papagei_niederha-0.0.2.dist-info/METADATA
papagei_niederha-0.0.2.dist-info/WHEEL
papagei_niederha-0.0.2.dist-info/top_level.txt
papagei_niederha-0.0.2.dist-info/RECORD
