Metadata-Version: 2.1
Name: papagei-niederha
Version: 0.0.2
Summary: A package for easy verbose logging, error and warnings.
Home-page: https://github.com/niederha/papagei
Author: Niederhauser Loïc
Author-email: loic.niederhauser@gmail.com
License: UNKNOWN
Platform: UNKNOWN
Classifier: Programming Language :: Python :: 3
Classifier: License :: OSI Approved :: MIT License
Classifier: Operating System :: OS Independent
